metapg/py.typed
metapg/dev/__init__.py
metapg/dev/py.typed
metapg/dev/testing/__init__.py
metapg/dev/testing/setup.py
metapg_dev-0.0.1.dist-info/METADATA
metapg_dev-0.0.1.dist-info/WHEEL
metapg_dev-0.0.1.dist-info/RECORD
