Metadata-Version: 2.4
Name: metapg-dev
Version: 0.0.1
Summary: Development tools and dependencies for metapg
Project-URL: Homepage, https://github.com/metapg/metapg
Project-URL: Documentation, https://github.com/metapg/metapg#readme
Project-URL: Repository, https://github.com/metapg/metapg
Project-URL: Issues, https://github.com/metapg/metapg/issues
Author-email: Darwin Monroy <darwin@ideatives.com>
License: MIT
Keywords: async,database,development,migration,pool,postgresql
Classifier: Development Status :: 4 - Beta
Classifier: Intended Audience :: Developers
Classifier: License :: OSI Approved :: MIT License
Classifier: Programming Language :: Python :: 3
Classifier: Programming Language :: Python :: 3.11
Classifier: Programming Language :: Python :: 3.12
Classifier: Programming Language :: Python :: 3.13
Classifier: Topic :: Database
Classifier: Topic :: Software Development :: Libraries :: Python Modules
Requires-Python: >=3.11
Requires-Dist: black>=24.0.0
Requires-Dist: build>=1.0.0
Requires-Dist: hatchling>=1.0.0
Requires-Dist: ipdb
Requires-Dist: ipython
Requires-Dist: mypy>=1.11.0
Requires-Dist: pytest-asyncio>=0.24.0
Requires-Dist: pytest-cov>=5.0.0
Requires-Dist: pytest>=8.0.0
Requires-Dist: ruff>=0.6.0
